trulogger/__init__.py
TruLogger-1.1.9.dist-info/METADATA
TruLogger-1.1.9.dist-info/WHEEL
TruLogger-1.1.9.dist-info/top_level.txt
TruLogger-1.1.9.dist-info/RECORD
