Metadata-Version: 2.1
Name: TruLogger
Version: 1.1.9
Author-email: Jacob Truman <jacob.truman@gmail.com>
Project-URL: homepage, https://github.com/jacobtruman/TruLogger
Project-URL: documentation, https://github.com/jacobtruman/TruLogger
Project-URL: repository, https://github.com/jacobtruman/TruLogger
Requires-Python: <4,>=3.7
